exceltidy/__init__.py
exceltidy/config.py
exceltidy/exceltidy.py
exceltidy-0.0.3.dist-info/LICENSE
exceltidy-0.0.3.dist-info/METADATA
exceltidy-0.0.3.dist-info/WHEEL
exceltidy-0.0.3.dist-info/top_level.txt
exceltidy-0.0.3.dist-info/RECORD
