Metadata-Version: 2.1
Name: exceltidy
Version: 0.0.3
Summary: Based on openpyxl and xlwings to facilitate Excel processing
Home-page: https://github.com/cmacckk/exceltidy
Author: cmacckk
Author-email: emailforgty@163.com
Classifier: Programming Language :: Python :: 3
Classifier: License :: OSI Approved :: GNU General Public License v3 (GPLv3) 
Requires-Python: >=3.6
License-File: LICENSE
Requires-Dist: xlwings
Requires-Dist: openpyxl
